LICENSE
MANIFEST.in
README.org
README.rst
pyproject.toml
setup.cfg
setup.py
django_juss2.egg-info/PKG-INFO
django_juss2.egg-info/SOURCES.txt
django_juss2.egg-info/dependency_links.txt
django_juss2.egg-info/requires.txt
django_juss2.egg-info/top_level.txt
juss/__init__.py
juss/admin.py
juss/apis.py
juss/apps.py
juss/forms.py
juss/middlewares.py
juss/models.py
juss/serializers.py
juss/tests.py
juss/urls.py
juss/views.py
juss/widgets.py
juss/migrations/0001_initial.py
juss/migrations/0002_rename_model_menu_content_type.py
juss/migrations/__init__.py
juss/static/admin/img/icon-addlink.svg
juss/static/admin/img/icon-changelink.svg
juss/static/admin/img/icon-deletelink.svg
juss/static/admin/img/icon-no.svg
juss/static/admin/img/icon-yes.svg
juss/static/admin/img/tooltag-add.svg
juss/static/juss/app.css
juss/static/juss/bulma.min.css
juss/static/juss/check.svg
juss/static/juss/chevron-right.svg
juss/static/juss/feather.min.js
juss/static/juss/index.js.map
juss/static/juss/jdenticon.js
juss/static/juss/js.cookie.min.js
juss/static/juss/juss.js
juss/static/juss/img/bg.jpg
juss/templates/admin/actions.html
juss/templates/admin/base.html
juss/templates/admin/change_form.html
juss/templates/admin/change_form_object_tools.html
juss/templates/admin/change_list.html
juss/templates/admin/change_list_object_tools.html
juss/templates/admin/change_list_results.html
juss/templates/admin/delete_confirmation.html
juss/templates/admin/delete_selected_confirmation.html
juss/templates/admin/filter.html
juss/templates/admin/index.html
juss/templates/admin/login.html
juss/templates/admin/login_default.html
juss/templates/admin/mptt_change_list_results.html
juss/templates/admin/object_history.html
juss/templates/admin/pagination.html
juss/templates/admin/search_form.html
juss/templates/admin/submit_line.html
juss/templates/admin/auth/user/add_form.html
juss/templates/admin/auth/user/change_password.html
juss/templates/admin/edit_inline/stacked.html
juss/templates/admin/edit_inline/tabular.html
juss/templates/admin/includes/fieldset.html
juss/templates/admin/widgets/clearable_file_input.html
juss/templates/admin/widgets/clearable_image_input.html
